xfunctions/__init__.py
xfunctions/xfunctions.py
xfunctions-0.1.15.dist-info/LICENSE
xfunctions-0.1.15.dist-info/METADATA
xfunctions-0.1.15.dist-info/WHEEL
xfunctions-0.1.15.dist-info/top_level.txt
xfunctions-0.1.15.dist-info/RECORD
